wyze_sdk/__init__.py
wyze_sdk/version.py
wyze_sdk/api/__init__.py
wyze_sdk/api/base.py
wyze_sdk/api/client.py
wyze_sdk/api/events.py
wyze_sdk/api/devices/__init__.py
wyze_sdk/api/devices/bulbs.py
wyze_sdk/api/devices/cameras.py
wyze_sdk/api/devices/locks.py
wyze_sdk/api/devices/plugs.py
wyze_sdk/api/devices/scales.py
wyze_sdk/api/devices/sensors.py
wyze_sdk/api/devices/switches.py
wyze_sdk/api/devices/thermostats.py
wyze_sdk/api/devices/vacuums.py
wyze_sdk/errors/__init__.py
wyze_sdk/models/__init__.py
wyze_sdk/models/devices/__init__.py
wyze_sdk/models/devices/base.py
wyze_sdk/models/devices/bulbs.py
wyze_sdk/models/devices/cameras.py
wyze_sdk/models/devices/lights.py
wyze_sdk/models/devices/locks.py
wyze_sdk/models/devices/plugs.py
wyze_sdk/models/devices/scales.py
wyze_sdk/models/devices/sensors.py
wyze_sdk/models/devices/switches.py
wyze_sdk/models/devices/thermostats.py
wyze_sdk/models/devices/vacuums.py
wyze_sdk/models/events/__init__.py
wyze_sdk/service/__init__.py
wyze_sdk/service/api_service.py
wyze_sdk/service/auth_service.py
wyze_sdk/service/base.py
wyze_sdk/service/earth_service.py
wyze_sdk/service/ford_service.py
wyze_sdk/service/general_api_service.py
wyze_sdk/service/platform_service.py
wyze_sdk/service/pluto_service.py
wyze_sdk/service/scale_service.py
wyze_sdk/service/sirius_service.py
wyze_sdk/service/venus_service.py
wyze_sdk/service/wyze_response.py
wyze_sdk/signature/__init__.py
wyze_sdk_aldilaff-2.2.1.dist-info/licenses/LICENSE
wyze_sdk_aldilaff-2.2.1.dist-info/METADATA
wyze_sdk_aldilaff-2.2.1.dist-info/WHEEL
wyze_sdk_aldilaff-2.2.1.dist-info/top_level.txt
wyze_sdk_aldilaff-2.2.1.dist-info/RECORD
