Metadata-Version: 2.4
Name: wyze-sdk-aldilaff
Version: 2.2.1
Summary: The Wyze Labs API Platform SDK for Python (fork with HL_A19C2 support).
Home-page: https://github.com/aldilaff/wyze-sdk
Author: Faisal Aldilaijan (fork), Shaun Tarves (original)
Author-email: github@faisal.software
License: The Unlicense
Keywords: wyze,wyze-labs,wyze-sdk,wyze-api,wyzeapy,wyze-apy,smart home,home automation
Classifier: Development Status :: 5 - Production/Stable
Classifier: Topic :: Communications :: Chat
Classifier: License :: Public Domain
Classifier: License :: Free for non-commercial use
Classifier: Operating System :: OS Independent
Classifier: Programming Language :: Python
Classifier: Topic :: Software Development :: Libraries :: Python Modules
Classifier: Topic :: Home Automation
Classifier: Programming Language :: Python :: 3
Classifier: Programming Language :: Python :: 3.8
Classifier: Programming Language :: Python :: 3.9
Requires-Python: >=3.8.0
License-File: LICENSE
Requires-Dist: requests
Requires-Dist: blackboxprotobuf
Requires-Dist: mintotp
Requires-Dist: pycryptodomex
Dynamic: author
Dynamic: author-email
Dynamic: classifier
Dynamic: description
Dynamic: description-content-type
Dynamic: home-page
Dynamic: keywords
Dynamic: license
Dynamic: license-file
Dynamic: requires-dist
Dynamic: requires-python
Dynamic: summary
